scraping_pros/__init__.py
scraping_pros/client.py
scraping_pros/other_files.py
scrapingpros-0.1.12.dist-info/LICENSE
scrapingpros-0.1.12.dist-info/METADATA
scrapingpros-0.1.12.dist-info/WHEEL
scrapingpros-0.1.12.dist-info/top_level.txt
scrapingpros-0.1.12.dist-info/RECORD
