Metadata-Version: 2.1
Name: scrapingpros
Version: 0.1.12
Summary: Scraping Pros API Client
Home-page: https://gitlab.com/7Puentes/batua2/sprosdata-python
Author: Scraping Pros
Author-email: team@scrapingpros.com
Classifier: Programming Language :: Python :: 3
Classifier: License :: OSI Approved :: MIT License
Classifier: Operating System :: OS Independent
Requires-Python: >=3.6
License-File: LICENSE
Requires-Dist: requests
